torch_fem-0.5.1.dist-info/licenses/LICENSE
torchfem/__init__.py
torchfem/base.py
torchfem/elements.py
torchfem/examples.py
torchfem/homogenization.py
torchfem/io.py
torchfem/materials.py
torchfem/mesh.py
torchfem/planar.py
torchfem/plot_utils.py
torchfem/rotations.py
torchfem/sdfs.py
torchfem/shell.py
torchfem/solid.py
torchfem/sparse.py
torchfem/truss.py
torchfem/utils.py
torchfem/data/clamped_plate_uniform_S8R.vtk
torchfem/data/extruded_hex_mesh.inp
torchfem/data/fillet.vtu
torchfem/data/ge_bracket.vtu
torchfem/data/iso37.vtu
torchfem/data/plate_hole.vtk
torchfem/data/quarter_plate_hole_3d.vtu
torch_fem-0.5.1.dist-info/METADATA
torch_fem-0.5.1.dist-info/WHEEL
torch_fem-0.5.1.dist-info/top_level.txt
torch_fem-0.5.1.dist-info/RECORD
