Metadata-Version: 2.4
Name: torch-fem
Version: 0.5.1
Summary: GPU accelerated differential finite elements for solid mechanics with PyTorch.
Author-email: Nils Meyer <nils.meyer@uni-a.de>
License: Copyright 2024 Nils Meyer
Project-URL: source, https://github.com/meyer-nils/torch-fem
Keywords: finite elements,automatic differentiation
Classifier: Programming Language :: Python
Classifier: Programming Language :: Python :: 3
Classifier: Programming Language :: Python :: 3.10
Classifier: Programming Language :: Python :: 3.11
Classifier: Programming Language :: Python :: 3.12
Classifier: Programming Language :: Python :: 3.13
Requires-Python: >=3.10
License-File: LICENSE
Requires-Dist: ipywidgets
Requires-Dist: ipykernel
Requires-Dist: matplotlib
Requires-Dist: memory_profiler
Requires-Dist: meshio
Requires-Dist: pyamg
Requires-Dist: pyvista
Requires-Dist: scipy~=1.15.0
Requires-Dist: tqdm
Requires-Dist: torch
Requires-Dist: trame
Requires-Dist: trame-vuetify
Requires-Dist: trame-vtk
Requires-Dist: imageio
Dynamic: license-file
